promotion/__init__.py
promotion/__version__.py
promotion/camouflage.py
promotion/extractor.py
promotion/guise.py
promotion/search_engin.py
promotion/test.py
promotion/test_translate.py
promotion/translate.py
promotion/translate3.py
promotion/translator.py
promotion/wordpress_release.py
promotion-1.0.2.dist-info/METADATA
promotion-1.0.2.dist-info/RECORD
promotion-1.0.2.dist-info/WHEEL
promotion-1.0.2.dist-info/top_level.txt
