Metadata-Version: 2.1
Name: promotion
Version: 1.0.2
Summary: Promotion tools.
Home-page: https://bitbucket.org/rabintang/seo_utils
Author: Rabin Tang
Author-email: bintang.hit@gmail.com
License: MIT
Platform: UNKNOWN
Classifier: License :: OSI Approved :: MIT License
Classifier: Programming Language :: Python
Classifier: Programming Language :: Python :: 2
Classifier: Programming Language :: Python :: 2.7
Classifier: Programming Language :: Python :: Implementation :: CPython
Classifier: Programming Language :: Python :: Implementation :: PyPy
Requires-Python: >=2.7.0
Requires-Dist: python-wordpress-xmlrpc
Requires-Dist: tencentcloud-sdk-python
